journald_mcp_server/__init__.py
journald_mcp_server/datetime_utils.py
journald_mcp_server/server.py
journald_mcp_server-0.1.0.dist-info/licenses/LICENSE
journald_mcp_server-0.1.0.dist-info/METADATA
journald_mcp_server-0.1.0.dist-info/WHEEL
journald_mcp_server-0.1.0.dist-info/entry_points.txt
journald_mcp_server-0.1.0.dist-info/top_level.txt
journald_mcp_server-0.1.0.dist-info/RECORD
