Metadata-Version: 2.4
Name: journald-mcp-server
Version: 0.1.0
Summary: MCP server for journald
License-Expression: MIT
Requires-Python: >=3.12
License-File: LICENSE
Requires-Dist: mcp[cli]>=1.23.1
Requires-Dist: systemd-python>=235
Requires-Dist: click>=8.2.0
Requires-Dist: dateparser>=1.2.0
Dynamic: license-file
